{
  "id": "ge-doc-109090",
  "type": "statute",
  "title": "თავისუფლების აღკვეთით მსჯავრდებულ პირთა სასჯელის მოსახდელად იმ სახელმწიფოსათვის გადაცემის შესახებ, რომლის მოქალაქენი ისინი არიან",
  "short_name": "DOC-109090",
  "status": "in_force",
  "issued_date": "1996-11-19",
  "in_force_date": "1996-11-19",
  "url": "https://www.matsne.gov.ge/ka/document/view/109090?publication=2",
  "description": "Official consolidated legislation text published by the Legislative Herald of Georgia (matsne.gov.ge).",
  "provisions": [
    {
      "provision_ref": "art1",
      "section": "1",
      "title": "ბრძანებულება №754",
      "content": "საქართველოს პრეზიდენტის\nბრძანებულება №754\n1996 წლის 19 ნოემბერი\nქ. თბილისი\nთავისუფლების აღკვეთის მსჯავრდებულ პირთა სასჯელის მოსახდელად იმ სახელმწიფოსთვის გადაცემის შესახებ, რომლის მოქალაქენიც ისინი არიან\n1. საქართველოს და საზღვარგარეთის ქვეყნებს შორის თავისუფლების აღკვეთით მსჯავრდებულ პირთა სასჯელის მოსახდელად გადაცემის შესახებ დადებულ საერთაშორისო ხელშეკრულებებით ნაკისრ ვალდებულებათა შესრულებისას სახელმწიფო დაწესებულებები ხელმძღვანელობენ აღნიშნული ხელშეკრულებებით, საქართველოს კანონმდებლობით და ამ ბრძანებულებით.\n2. თავისუფლების აღკვეთით მსჯავრდებულ პირთა სასჯელის მოსახდელად იმ სახელმწიფოსათვის გადაცემის საკითხს, რომლის მოქალაქენიც ისინი არიან, განიხილავს საქართველოს იუსტიციის სამინისტრო.\n3. გადაწყვეტილება მსჯავრდებულის გადაცემის შესახებ საქართველოს იუსტიციის სამინისტრომ შეიძლება მიიღოს როგორც საზღვარგარეთის ქვეყნის კომპეტენტური ორგანოს თხოვნის, ისე მსჯავრდებულის, მისი ნათესავების ან კანონიერი წარმომადგენლის შუამდგომლობის საფუძველზე.\n4. საბოლოო გადაწყვეტილებას მსჯავრდებულის გადაცემის შესახებ იღებს საქართველოს იუსტიციის სამინისტრო საქართველოს პროკურატურასთან და საქართველოს შინაგან საქმეთა სამინისტროსთან წინასწარი შეთანხმებით.\n5. საზღვარგარეთის ქვეყნების სასამართლოების მიერ მსჯავრდებული საქართველოს მოქალაქეების, აგრეთვე საქართველოს სასამართლოების მიერ მსჯავრდებული უცხოელი მოქალაქეების გადაცემას მიღებული გადაწყვეტილების საფუძველზე ახორციელებს საქართველოს შინაგან საქმეთა სამინისტრო.\n6. თავისუფლების აღკვეთით სჯავრდებულ პირთა სასჯელის მოსახდელ ნაწილსა და რეჟიმს განსაზღვრავს სასამართლო კანონმდებლობით დადგენილი წესით.\n7. მსჯავრდებულის სასჯელის მოსახდელად გადაცემისათვის საჭირო სახსრები შეიძლება გაიღონ მსჯავრდებულმა, მისმა ნათესავებმა ან კანონმიერმა წარმომადგენელმა დადგენილი წესის შესაბამისად.\n8. საქართველოს იუსტიციის სამინისტრომ და შინაგან საქმეთა სამინისტრომ ერთ თვეში შეიმუშაონ ინსტრუქცია თავისუფლების აღკვეთით მსჯავრდებულ პირთა სასჯელის მოსახდელად იმ სახელმწიფოსათვის გადაცემის შესახებ, რომლის მოქალაქენიც ისინი არიან.\nე. შევარდნაძე"
    }
  ],
  "definitions": []
}
