{
  "id": "ge-doc-2376500",
  "type": "statute",
  "title": "კიბოს პოპულაციური რეგისტრის დანერგვის მიზნით გასატარებელი ღონისძიებების შესახებ",
  "short_name": "DOC-2376500",
  "status": "in_force",
  "issued_date": "2014-06-09",
  "in_force_date": "2014-06-09",
  "url": "https://www.matsne.gov.ge/ka/document/view/2376500",
  "description": "Official consolidated legislation text published by the Legislative Herald of Georgia (matsne.gov.ge).",
  "provisions": [
    {
      "provision_ref": "art1",
      "section": "1",
      "title": "ე) კიბოს პოპულაციური რეგისტრის წარმოებისათვის საჭირო ფორმების ჩამონათვალი და მათი წარდგენის წესი და ვადები განისაზღვროს საქართველოს შრომის, ჯანმრთელობისა და სოციალური დაცვის მინისტრის შესაბამისი ნორმატიული აქტით.",
      "content": "საქართველოს მთავრობის\nგანკარგულება №1023\n2014 წლის 9 ივნისი\nქ. თბილისი\nკიბოს პოპულაციური რეგისტრის დანერგვის მიზნით გასატარებელი ღონისძიებების შესახებ\n1. საქართველოში ონკოდაავადებების აღრიცხვიანობის გაუმჯობესების მიზნით, ქვეყნის მასშტაბით კიბოს პოპულაციური რეგისტრის დანერგვისათვის განხორციელდეს შემდეგი ღონისძიებები:\nა) ონკოლოგიური პროფილის სამედიცინო პერსონალის სწავლება ონკოლოგიაში დაავადებათა საერთაშორისო კლასიფიკატორის (ICD-O) ეფექტიანი გამოყენებისა და კიბოს სარეგისტრაციო ფორმების სწორად შევსების მიზნით;\nბ) კიბოს პოპულაციური რეგისტრის მონაცემთა რეგისტრატორების რეტრენინგი;\nგ) კიბოს პოპულაციური რეგისტრის CanReg5 პროგრამის ტექნიკური და პროგრამული უზრუნველყოფა;\nდ) კიბოს პოპულაციური რეგისტრის მენეჯმენტი (საკონსულტაციო მომსახურება, კიბოს პოპულაციის რეგისტრის დანერგვის პროცესის მონიტორინგი);\nე) კიბოს პოპულაციური რეგისტრის წარმოებისათვის საჭირო ფორმების ჩამონათვალი და მათი წარდგენის წესი და ვადები განისაზღვროს საქართველოს შრომის, ჯანმრთელობისა და სოციალური დაცვის მინისტრის შესაბამისი ნორმატიული აქტით.\n2. ამ განკარგულების შესრულების მიზნით:\nა) დაევალოს საქართველოს შრომის, ჯანმრთელობისა და სოციალური დაცვის სამინისტროს (შემდგომში – სამინისტრო) უზრუნველყოს შესაბამისი ღონისძიებებისათვის საჭირო ქმედებების განხორციელება;\nბ) დაევალოს სამინისტროს სახელმწიფო კონტროლს დაქვემდებარებულ სსიპ – ლ. საყვარელიძის სახელობის დაავადებათა კონტროლისა და საზოგადოებრივი ჯანმრთელობის ეროვნულ ცენტრს (შემდგომში – ცენტრი) უზრუნველყოს ქვეყნის მასშტაბით კიბოს პოპულაციური რეგისტრის დასანერგად საჭირო ღონისძიებების განხორციელება.\n3. ამ განკარგულებით განსაზღვრული მომსახურების სახელმწიფო შესყიდვა ცენტრმა განახორციელოს „სახელმწიფო შესყიდვების შესახებ“ საქართველოს კანონის 10^1 მუხლის მე-3 პუნქტის „დ“ ქვეპუნქტის შესაბამისად, გამარტივებული შესყიდვის საშუალებით.\n4. ამ განკარგულებით განსაზღვრული ღონისძიებების დაფინანსება განხორციელდეს „საქართველოს 2014 წლის სახელმწიფო ბიუჯეტის შესახებ“ საქართველოს კანონით პროგრამისათვის ,,დაავადებათა ადრეული გამოვლენა და სკრინინგი“ (პროგრამული კოდი – 35 03 03 01) გათვალისწინებული საბიუჯეტო ასიგნებებიდან. შესაბამისად, აღნიშნული ღონისძიებების უზრუნველსაყოფად, პროგრამისათვის ,,დაავადებათა ადრეული გამოვლენა და სკრინინგი“ გათვალისწინებული ასიგნებებიდან გამოიყოს 28,700 ლარი.\nპრემიერ-მინისტრი ირაკლი ღარიბაშვილი"
    }
  ],
  "definitions": []
}
