{
  "id": "ge-doc-57826",
  "type": "statute",
  "title": ",,საქართველოს ფინანსთა მინისტრის ზოგიერთი ბრძანებულების ძალადაკარგულად ცნობის თაობაზე”",
  "short_name": "DOC-57826",
  "status": "in_force",
  "issued_date": "2004-03-25",
  "in_force_date": "2004-03-25",
  "url": "https://www.matsne.gov.ge/ka/document/view/57826",
  "description": "Official consolidated legislation text published by the Legislative Herald of Georgia (matsne.gov.ge).",
  "provisions": [
    {
      "provision_ref": "art1",
      "section": "1",
      "title": "მუხლი 1. ძალადაკარგულად ჩაითვალოს საქართველოს ფინანსთა მინისტრის შემდეგი ბრძანებები:",
      "content": "1. საქართველოს ფინანსთა მინისტრის 1997 წლის 8 აგვისტოს №192 ბრძანება „აქციზური მარკების შემოღებამდე თამბაქოს ნაწარმის შემოტანის დროებითი წესის გაგრძელების შესახებ”;\n2. საქართველოს ფინანსთა მინისტრის 1998 წლის 2 ივნისის №139 ბრძანება „აქციზური მარკების ბეჭდვასა და მიწოდების თაობაზე ტენდერის ჩატარებასთან დაკავშირებით კომისიის შექმნის შესახებ”;\n3. საქართველოს ფინანსთა მინისტრის 1998 წლის 16 მარტის №68 ბრძანება „ნავთობპროდუქტების დაბეგვრის შემდგომი გაუმჯობესების ღონისძიებათა შესახებ”;\n4. საქართველოს ფინანსთა მინისტრის 1998 წლის 10 აპრილის №93 ბრძანება „გრანტებით შემოტანილი ნავთობპროდუქტების საბაჟო გაფორმების შესახებ”;\n5. საქართველოს ფინანსთა მინისტრისა და საქართველოს სახელმწიფო საგადასახადო სამსახურის უფროსის 1999 წლის 25 თებერვლის №52/41 ერთობლივი ბრძანება „აქციზური მარკების რეალიზაციის შესახებ ინფორმაციის საგადასახადო ორგანოებზე გადაცემის თაობაზე”;\n6. საქართველოს ფინანსთა მინისტრისა და საქართველოს სახელმწიფო საგადასახადო სამსახურის უფროსის 1999 წლის 5 მარტის №58/42 ერთობლივი ბრძანება „დროებითი აქციზური მარკების დამზადების, გაცემისა და აქციზური საქონლის ნაშთების ნიშანდების წესის თაობაზე”;\n7. საქართველოს ფინანსთა მინისტრის 1999 წლის 19 აპრილის №87 ბრძანება „დროებითი აქციზური მარკების განადგურების შესახებ”;\n8. საქართველოს ფინანსთა მინისტრის 1999 წლის 30 აპრილის №99 ბრძანება „იმპორტული დაბალი ხარისხის თამბაქოს ნაწარმისათვის განკუთვნილი აქციზური მარკების რეალიზაციის (გაცემის) შესახებ”;\n9. საქართველოს ფინანსთა მინისტრის 1999 წლის 27 მაისის №130 ბრძანება „შპს „სთრაიქის“ სახელზე გაცემული აქციზური მარკების შპს „ტაო+”-ზე გადაფორმების შესახებ”;\n10. საქართველოს სახელმწიფო საგადასახადო სამსახურის უფროსის 1999 წლის 28 სექტემბრის №233 ბრძანება „ლუდზე აქციზური მარკების შემოღების შ ე სახებ”;\n11. საქართველოს ფინანსთა მინისტრისა და საქართველოს სახელმწიფო საგადასახადო სამსახურის უფროსის 1999 წლის 12 ნოემბრის №243/272 ერთობლივი ბრძანება „საბითუმო საცალო ქსელის საწარმოებში მარკირებას დაქვემდებარებული ლუდის ნაშთებზე აქციზური მარკების გაცემისა და მარკირების შესახებ”;\n12. საქართველოს ფინანსთა მინისტრის 1999 წლის 16 ნოემბრის №245 ბრძანება „აჭარის ავტონომიური რესპუბლიკის საბითუმო საცალო ქსელის საწარმოებში მარკირებას დაქვემდებარებული ლუდის ნაშთებზე აქციზური მარკების გაცემისა და მარკირების შესახებ”;\n13. საქართველოს ფინანსთა მინისტრის 1999 წლის 27 დეკემბრის №259 ბრძანება „ადგილობრივი თამბაქოს ნაწარმისათვის განკუთვნილი აქციზური მარკების რეალიზაციის (გაცემის) შესახებ”;\n14. საქართველოს ფინანსთა მინისტრის 1999 წლის 29 დეკემბრის №262 ბრძანება „ცხინვალის რეგიონში რეგისტრირებული მეწარმე სუბიექტებისათვის ადგილობრივი წარმოების ლუდისა და ალკოჰოლიანი სასმელების აქციზური მარკების გაცემის შესახებ”;\n15. საქართველოს ფინანსთა მინისტრის 2000 წლის 4 იანვრის №1 ბრძანება „ლუდისათვის განკუთვნილი უნომრო აქციზური მარკების გამოუყენებლად ცნობისა და განადგურების შესახებ”;\n16. საქართველოს ფინანსთა მინისტრის 2000 წლის 1 თებერვლის №12 ბრძანება „ადგილობრივი ალკოჰოლური ნაწარმისათვის განკუთვნილი აქციზური მარკების რეალიზაციის (გაცემის) შესახებ”;\n17. საქართველოს ფინანსთა მინისტრის 2000 წლის 11 თებერვლის №15 ბრძანება „დროებითი აქციზური მარკებით ნიშანდებული ალკოჰოლიანი სასმელებით ხელმეორედ ნიშანდების შესახებ”;\n18. საქართველოს ფინანსთა მინისტრის 2002 წლის 27 ივნისის №193 ბრძანება „ნავთობპროდუქტების, ეთილის სპირტის და სპირტიანი სასმელების მიწოდების აღრიცხვის და დაბეგვრის კონტროლის ღონისძიებათა შესახებ”;\n19. საქართველოს ფინანსთა მინისტრის 2003 წლის 27 თებერვლის №92 ბრძანება „საქართველოს ფინანსთა სამინისტროს აქციზური მარკების სამსახურის დებულების დამტკიცების თაობაზე”;\n20. საქართველოს ფინანსთა მინისტრის 2004 წლის 28 იანვრის №39 ბრძანება „საქართველოში აქციზური მარკების აღრიცხვის, რეალიზაციისა და კონტროლის წესის შესახებ დებულების დამტკიცების თაობაზე”."
    },
    {
      "provision_ref": "art2",
      "section": "2",
      "title": "მუხლი 2.",
      "content": "ეს ბრძანება ამოქმედდეს გამოქვეყნებისთანავე.\nზ. ნოღაიდელი"
    }
  ],
  "definitions": []
}
