{
  "id": "ge-doc-2987399",
  "type": "statute",
  "title": "ყვარლის მუნიციპალიტეტის სასარგებლო წიაღისეულის მოპოვების ლიცენზიისაგან გათავისუფლების თაობაზე",
  "short_name": "DOC-2987399",
  "status": "in_force",
  "issued_date": "2015-09-14",
  "in_force_date": "2015-09-14",
  "url": "https://www.matsne.gov.ge/ka/document/view/2987399",
  "description": "Official consolidated legislation text published by the Legislative Herald of Georgia (matsne.gov.ge).",
  "provisions": [
    {
      "provision_ref": "art1",
      "section": "1",
      "title": "1. „სასარგებლო წიაღისეულის მოპოვების ლიცენზიის გაცემის წესისა და პირობების შესახებ დებულების დამტკიცების თაობაზე“ საქართველოს მთავრობის 2005 წლის 11 აგვისტოს №136 დადგენილებით დამტკიცებული დებულების (შემდგომში − დებულება) 7^4 მუხლის საფუძვე",
      "content": "საქართველოს მთავრობის\nგანკარგულება №1985\n2015 წლის 14 სექტემბერი\nქ. თბილისი\nყვარლის მუნიციპალიტეტის სასარგებლო წიაღისეულის მოპოვების ლიცენზიისაგან გათავისუფლების თაობაზე\n1. „სასარგებლო წიაღისეულის მოპოვების ლიცენზიის გაცემის წესისა და პირობების შესახებ დებულების დამტკიცების თაობაზე“ საქართველოს მთავრობის 2005 წლის 11 აგვისტოს №136 დადგენილებით დამტკიცებული დებულების (შემდგომში − დებულება) 7^4 მუხლის საფუძველზე, სახელმწიფოებრივი და საზოგადოებრივი ინტერესების გათვალისწინებით, სტიქიისგან დაზარალებული და სიღარიბის ზღვარს მიღმა მყოფი მოსახლეობის საცხოვრებელი სახლების შეკეთებისა და სასოფლო-სამეურნეო სავარგულამდე მისასვლელი გზების რეაბილიტაციის მიზნით, ყვარლის მუნიციპალიტეტი სამი თვის ვადით გათავისუფლდეს სასარგებლო წიაღისეულის (ქვიშა-ხრეშის) მოპოვების ლიცენზიისაგან ყვარლის მუნიციპალიტეტის ტერიტორიაზე, შემდეგ X და Y კოორდინატების საზღვრებში:\nა) ქალაქ ყვარლის მიმდებარე ტერიტორია − 2000 მ^3ქვიშა-ხრეში:\n№\nX\nY\n1\n566069\n4644114\n2\n566118\n4644109\n3\n566101\n4644064\n4\n566060\n4644072\nS = 0,2ჰა\nWGS 1984;\nბ) სოფ. შილდას მიმდებარე ტერიტორია − 1000 მ^3 ქვიშა-ხრეში:\n№\nX\nY\n1\n556993\n4648357\n2\n557018\n4648347\n3\n556997\n4648313\n4\n556975\n4648323\nS = 0, 1 ჰა\nWGS 1984.\n2. ლიცენზიისაგან გათავისუფლებული პირი − ყვარლის მუნიციპალიტეტი ვალდებულია:\nა) უზრუნველყოს საქართველოს გარემოსა და ბუნებრივი რესურსების დაცვის სამინისტროს სსიპ − გარემოს ეროვნული სააგენტოს შესაბამისი დასკვნებით (გეოსაინფორმაციო პაკეტები) განსაზ­ღვრული პირობების შესრულება;\nბ) მოპოვებული სასარგებლო წიაღისეული გამოიყენოს მხოლოდ ამ განკარგულების პირველი პუნქტით განსაზღვრული მიზნისათვის;\nგ) დებულების 7^4 მუხლის 2^1 პუნქტის შესაბამისად, ყვარლის მუნიციპალიტეტმა სასარგებლო წიაღისეულის მოპოვების ლიცენზიისაგან გათავისუფლებისათვის, ამ განკარგულების ძალაში შესვლიდან ერთი თვის ვადაში, უზრუნველყოს საქართველოს სახელმწიფო ბიუჯეტში შემდეგი ოდენობის თანხების გადახდა:\nგ.ა) ქ. ყვარლის მიმდებარე ტერიტორიაზე 2 000 მ^3ქვიშა-ხრეშის მოპოვებისთვის − 348 (სამას ორმოცდარვა) ლარი;\nგ.ბ) სოფ. შილდას მიმდებარე ტერიტორიაზე 1000 მ^3ქვიშა-ხრეშის მოპოვებისთვის − 174 (ას სამოცდათოთხმეტი) ლარი.\n3. ყვარლის მუნიციპალიტეტის მიერ ლიცენზიისაგან გათავისუფლების საფუძველზე მოპოვებული სასარგებლო წიაღისეულის მიზნობრივად გამოყენების ზედამხედველობა განახორციელოს საქართველოს გარემოსა და ბუნებრივი რესურსების დაცვის სამინისტროს სახელმწიფო საქვეუწყებო დაწესებულებამ − გარემოსდაცვითი ზედამხედველობის დეპარტამენტმა (შემდგომში − გარემოსდაცვითი ზედამხედველობის დეპარტამენტი).\n4. ყვარლის მუნიციპალიტეტმა სასარგებლო წიაღისეულის მოპოვების ვადის გასვლიდან ორი კვირის ვადაში გარემოსდაცვითი ზედამხედველობის დეპარტამენტში წარადგინოს ინფორმაცია მოპოვებული ბუნებრივი რესურსის ოდენობის შესახებ.\nპრემიერ-მინისტრი ი. ღარიბაშვილი"
    }
  ],
  "definitions": []
}
