{
  "id": "ge-doc-1343950",
  "type": "statute",
  "title": "სათამაშო ბიზნესის გადასახადის გადახდის ნიშნების ესკიზის დამტკიცების თაობაზე",
  "short_name": "DOC-1343950",
  "status": "in_force",
  "issued_date": "2004-12-31",
  "in_force_date": "2004-12-31",
  "url": "https://www.matsne.gov.ge/ka/document/view/1343950?publication=1",
  "description": "Official consolidated legislation text published by the Legislative Herald of Georgia (matsne.gov.ge).",
  "provisions": [
    {
      "provision_ref": "art1",
      "section": "1",
      "title": "ბრძანება №895",
      "content": "სახელმწიფო სარეგისტრაციო კოდი 200.110.010.22.033.006.969\nსაქართველოს ფინანსთა მინისტრის\nბრძანება №895\n2004 წლის 31 დეკემბერი\nქ. თბილისი\nსათამაშო ბიზნესის გადასახადის გადახდის ნიშნების ესკიზის დამტკიცების თაობაზე\nსაქართველოს საგადასახადო კოდექსის მე-3 მუხლის შესაბამისად და 280-ე მუხლის მე-6 ნაწილის აღსრულების მიზნით , ვბრძანებ:\n1. დამტკიცდეს სათამაშო ბიზნესის გადასახადის გადახდის ნიშნების ესკიზი.\n2. ბრძანება ამოქმედდეს 2005 წლის 1 იანვრიდან.\nზ. ნოღაიდელი\nსათამაშო ბიზნესის გადასახადის გადახდის ნიშნების ესკიზი\n1. სათამაშო ბიზნესის გადასახადის გადახდის ნიშნები ხუთი ტიპისაა (თან ერთვის):\nა) ნიშნები, რომლებიც გამოიყენება სათამაშო ავტომატების გადასახადით დაბეგვრისას წარწერით ,,სათამაშო აპარატი”;\nბ) ნიშნები, რომლებიც გამოიყენება სათამაშო მაგიდების გადასახადით დაბეგვრისას წარწერით ,,სათამაშო მაგიდა”;\nგ) ნიშნები, რომლებიც გამოიყენება ტოტალიზატორის სალაროს გადასახადით დაბეგვრისას წარწერით “ტოტალიზატორი”;\nდ) ნიშნები, რომლებიც გამოიყენება ბინგოს სალაროს გადასახადით დაბეგვრისას წარწერით “ბინგო”;\nე) ნიშნები, რომლებიც გამოიყენება ლოტოს სალაროს გადასახადით დაბეგვრისას წარწერით “ლოტო”.\n2. გადასახადის გადახდის ნიშნებში გამოიყენება 4 ფერი;\nა) სათამაშო აპარატებისათვის – მუქი ლურჯი, წითელი, რუხი და იისფერი;\nბ) სათამაშო მაგიდებისათვის – მუქი წითელი, წითელი, რუხი და იისფერი;\nგ) ტოტალიზატორის სალაროებისათვის – მუქი ყვითელი, წითელი, რუხი და იისფერი;\nდ) ბინგოს სალაროებისათვის – მუქი მწვანე, წითელი, რუხი და იისფერი;\nე) ლოტოს სალაროებისათვის – მუქი ყავისფერი, წითელი, რუხი და იისფერი;\n3. გადასახადის გადახდის ნიშანი გაყალბებისაგან დაცულია სპეციალური ელემენტებით.\n4. გადასახადის გადახდის ნიშანს გააჩნია სერია, ნომერი და გადასახადით დაბეგვრის პერიოდების აღნიშვნები ნიშანზე შეტანილია ნიშნის ქვედა ნაწილში კალენდარული თვეების აღმნიშვნელი 1-დან 12-ის ჩათვლით.\n5. გადასახადის გადახდის ნიშანი წარმოადგენს ფირნიშს, რომელიც დამზადებულია წებოვანი მასალისაგან და მისი აძრობის შემთხვევაში ზიანდება.\n6. გადასახადის გადახდის ნიშნის ზომებია – 60X95მმ."
    }
  ],
  "definitions": []
}
