{
  "id": "ge-doc-1596714",
  "type": "statute",
  "title": "ქ. თბილისის მერიის მიერ გრანტის მიღებაზე თანხმობის მიცემის შესახებ",
  "short_name": "DOC-1596714",
  "status": "in_force",
  "issued_date": "2012-02-24",
  "in_force_date": "2012-02-24",
  "url": "https://www.matsne.gov.ge/ka/document/view/1596714",
  "description": "Official consolidated legislation text published by the Legislative Herald of Georgia (matsne.gov.ge).",
  "provisions": [
    {
      "provision_ref": "art1",
      "section": "1",
      "title": "1. „ადგილობრივი თვითმმართველობის შესახებ“ საქართველოს ორგანული კანონის 22-ე მუხლის პირველი პუნქტის „ყ“ ქვეპუნქტის, „გრანტების შესახებ“ საქართველოს კანონის მე-4 მუხლის „გ“ ქვეპუნქტის და „საქართველოს დედაქალაქის – თბილისის შესახებ“ საქართველო",
      "content": "ქალაქ თბილისის საკრებულოს\nგადაწყვეტილება №2 - 5\n2012 წლი ს 24 თებერვალი\nქ. თბილისი\nქ. თბილისის მერიის მიერ გრანტის მიღებაზე თანხმობის მიცემის შესახებ\n1. „ადგილობრივი თვითმმართველობის შესახებ“ საქართველოს ორგანული კანონის 22-ე მუხლის პირველი პუნქტის „ყ“ ქვეპუნქტის, „გრანტების შესახებ“ საქართველოს კანონის მე-4 მუხლის „გ“ ქვეპუნქტის და „საქართველოს დედაქალაქის – თბილისის შესახებ“ საქართველოს კანონის მე-12 მუხლის „წ“ ქვეპუნქტის შესაბამისად, მიეცეს თანხმობა ქ. თბილისის მერიას, 2012 წელს მიიღოს გრანტი ევროკავშირის პროგრამის ,,ინვესტირება ადამიანურ რესურსებში (განვითარების და თანამშრომლობის ინსტრუმენტი) და აღმოსავლეთ პარტნიორობის კულტურული პროგრამა (ევროპის სამეზობლო პარტნიორობის ინსტრუმენტი)–უნარების გაძლიერება კულტურის სფეროში“ ფარგლებში , პროექტზე – ,,შემოქმედებითი ინდუსტრიების სექტორის გაძლიერება საქართველოში, აზერბაიჯანსა და სომხეთში. ტრადიციული რეწვა –ერთიანი პლატფორმა განვითარებისთვის“ .\n2. გადაწყვეტილება ძალაშია გამოქვეყნებისთანავე.\nსაკრებულოს თავმჯდომარე ზ. სამადაშვილი"
    }
  ],
  "definitions": []
}
