{
  "id": "ge-doc-83398",
  "type": "statute",
  "title": "„საქართველოს სოფლის მეურნეობის სამინისტროს იურიდიული დეპარტამენტის დებულების დამტკიცების შესახებ“",
  "short_name": "DOC-83398",
  "status": "in_force",
  "issued_date": "2009-04-14",
  "in_force_date": "2009-04-14",
  "url": "https://www.matsne.gov.ge/ka/document/view/83398?publication=5",
  "description": "Official consolidated legislation text published by the Legislative Herald of Georgia (matsne.gov.ge).",
  "provisions": [
    {
      "provision_ref": "art1",
      "section": "1",
      "title": "მუხლი 1. ზოგადი დებულებანი",
      "content": "1. საქართველოს სოფლის მეურნეობის სამინისტროს (შემდეგში – სამინისტრო) იურიდიული დეპარტამენტი (შემდეგში – დეპარტამენტი) წარმოადგენს სამინისტროს ცენტრალური აპარატის სტრუქტურულ ქვედანაყოფს.\n2. დეპარტამენტი, რომელიც შექმნილია სამინისტროს საქმიანობის ეფექტურად წარმართვის მიზნით, თავის საქმიანობაში ხელმძღვანელობს საქართველოს კონსტიტუციით, საერთაშორისო ხელშეკრულებებითა და შეთანხმებებით, საქართველოს საკანონმდებლო და კანონქვემდებარე ნორმატიული აქტებით და წინამდებარე დებულებით.\n3. დეპარტამენტი ანგარიშვალდებულია საქართველოს სოფლის მეურნეობის მინისტრის (შემდ გომში – მინისტრი) და მინისტრის მოადგილეების წინაშე. დეპარტამენტის ყოველდღიურ საქმიანობას კოორდინაციას უწევს კურატორი მინისტრის მოადგილე, რომელიც ახორციელებს დეპარტამენტის მიმართ სამსახურებრივ ზედამხედველობას კანონმდებლობით დადგენილი წესით."
    },
    {
      "provision_ref": "art2",
      "section": "2",
      "title": "მუხლი 2. დეპარტამენტის ფუნქციები და ამოცანები",
      "content": "დეპარტამენტის ფუნქციები და ამოცანებია:\nა) სხვა უწყებებიდან შემოსულ, აგრეთვე სამინისტროს სტრუქტურული ქვედანაყოფებისა და სამინისტროს სისტემის დაწესებულებების მიერ შემუშავებული ნორმატიული აქტების პროექტებზე სამართლებრივი დასკვნების მომზადება;\nბ) სამინისტროს სტრუქტურული ქვედანაყოფებისა და სამინისტროს სისტემის დაწესებულებების სამართლებრივი უზრუნველყოფა;\nგ) სამინისტროს საპარლამენტო მდივნისთვის “საპარლამენტო მდივნის შესახებ“ საქართველოს კანონით მინიჭებულ უფლებამოსილებათა განხორცილებისათვის ხელშეწყობა;\nდ) სამინისტროს პარლამენტთან ურთიერთობის კოორდინაცია;\nე) სამინისტროში და სამინისტროს სისტემის დაწესებულებებში მომზადებული საკანონმდებლო აქტების პროექტების კანონმდებლობით დადგენილი წესით პარლამენტში წარდგენის პროცედურების კოორდინაცია;\nვ) სასამართლოს დავებზე სამინისტროს წარმომადგენლობის უზრუნველყოფა;\nზ) მოქალაქეებისა და იურიდიული პირების განცხადებებისა და საჩივრების განხილვა და განხილვაში მონაწილეობის მიღება;\nთ) დამოუკიდებლად ან სამინისტროს სტრუქტურულ ქვედანაყოფებთან და სამინისტროს სისტემის დაწესებულებებთან ერთად ნორმატიული აქტების პროექტების შემუშავება;\nი) სამინისტროს კანონშემოქმედებითი საქმიანობის დაგეგმვის, სამინისტროში შესამუშავებელ კანონპროექტთა ნუსხის საბოლოო შეთანხმებისა და წარდგენის უზრუნველყოფის ორგანიზება საქართველოს მთავრობის საპარლამენტო მდივანთან;\nკ) სამინისტროს კანონშემოქმედებითი საქმიანობის გეგმით გათვალისწინებული საკითხების დადგენილ ვადებში გადაწყვეტის კოორდინაცია;\nლ) სამინისტროს მიერ ნაკისრი სახელშეკრულებო ვალდებულებათა მონიტორინგი;\nმ) საქართველოს კანონმდებლობით გათვალისწინებული სხვა ფუნქციები და ამოცანები."
    },
    {
      "provision_ref": "art3",
      "section": "3",
      "title": "მუხლი 3. დეპარტამენტის ხელმძღვანელობა და სტრუქტურა",
      "content": "1. დეპარტამენტს ხელმძღვანელობს დეპარტამენტის უფროსი, რომელსაც კანონმდებლობით დადგენილი წესით თანამდებობაზე ნიშნავს და თანამდებობიდან ათავისუფლებს მინისტრი.\n2. დეპარტამენტის უფროსი ანგარიშვალდებულია მინისტრისა და მინისტრის მოადგილეების წინაშე.\n3. დეპარტამენტის უფროსი:\nა) ხელმძღვანელობს და წარმართავს დეპარტამენტის საქმიანობას;\nბ) წარმოადგენს დეპარტამენტს დაკისრებული უფლება-მოვალეობების განხორციელებისას და პასუხისმგებელია დეპარტამენტზე დაკისრებული ფუნქციებისა და ამოცანების შესრულებაზე;\nგ) ანაწილებს მოვალეობებს დეპარტამენტის მოადგილესა და დეპარტამენტის სხვა მოხელეებს შორის, აძლევს მათ მითითებებსა და განკარგულებებს;\nდ) ზედამხედველობს დეპარტამენტის მოხელეების მიერ თავიანთი სამსახურებრივი მოვალეობების ჯეროვან შესრულებას, ახორციელებს მათ მიერ სამინისტროს შინაგანაწესის შესრულების კონტროლს;\nე) ახდენს სამინისტროს სტრუქტურული ქვედანაყოფებისა და სამინისტროს სისტემაში შემავალი დაწესებულებების მიერ შემუშავებულ სამართლებრივი აქტების პროექტების ვიზირებას;\nვ) მოთხოვნის შემთხვევაში წარადგენს ანგარიშს დეპარტამენტის მიერ გაწეული საქმიანობის შესახებ;\nზ) ორგანიზებას უკეთებს ამ დებულებით დეპარტამენტისათვის დაკისრებული ფუნქციების შესრულებას, რისთვისაც სამინისტროს ხელმძღვანელობას წარუდგენს წინადადებებს ცალკეული საკითხების მოწესრიგებისა და გადაწყვეტის თვალსაზრისით;\nთ) სამინისტროს ხელმძღვანელობას წარუდგენს წინადადებებს დეპარტამენტის შიდა სტრუქტურის, შტატების, მუშაობის ორგანიზაციის, დეპარტამენტის მოხელეების წახალისების, ან მათთვის დისციპლინური პასუხისმგებლობის დაკისრების შესახებ;\nი) შუამდგომლობს იმ სახსრების, მოწყობილობებისა და ინვენტარის გამოყოფაზე, რაც აუცილებელია დეპარტამენტის წინაშე მდგარი ფუნქციებისა და ამოცანების შესასრულებლად;\nკ) პერიოდულად ისმენს დეპარტამენტში შემავალი სტრუქტურული ქვედანაყოფების უფროსების ანგარიშს მათ მიერ გაწეული მუშაობის შესახებ;\nლ) შუამდგომლობს დეპარტამენტის მოხელეთა კვალიფიკაციის ამაღლებისა და გადამზადების თაობაზე;\nმ) ახორციელებს საქართველოს კანონდებლობით განსაზღვრულ სხვა ფუნქციებსა და ამოცანებს.\n4. დეპარტამენტის უფროსს ჰყავს მოადგილე, რომელსაც კანონმდებლობით დადგენილი წესით თანამდებობაზე ნიშნავს და თანამდებობიდან ათავისუფლებს მინისტრი.\n5. დეპარტამენტის უფროსის მოადგილის ფუნქციებს, უფლებამოსილებებს და საქმიანობის სფეროებს განსაზღვრავს დეპარტამენტის უფროსი.\n6. დეპარტამენტის უფროსის არყოფნის შემთხვევაში დეპარტამენტის უფროსის მოვალეობას ასრულებს მისი მოადგილე.\n7. დეპარტამენტის უფროსის მოადგილე:\nა) პასუხისმგებელია მინისტრის, მინისტრის მოადგილეებისა და დეპარტამენტის უფროსის წინაშე;\nბ) დეპარტამენტის უფროსის მიერ განსაზღვრული უფლებამოსილებებისა და საქმიანობის სფეროების გათვალისწინებით წარმართავს და ზედამხედველობას უწევს დეპარტამენტში შემავალი ცალკეული სტრუქტურული ქვედანაყოფების საქმიანობას;\nგ) მონაწილეობს დეპარტამენტში შემოსული მასალების განაწილებაში;\nდ) ზედამხედველობას უწევს დეპარტამენტის მოხელეთა მიერ სამსახურებრივი მოვალეობების შესრულებას;\nე) დეპარტამენტის უფროსის, მინისტრისა და მინისტრის მოადგილის დავალებით ახორციელებს სხვა უფლებამოსილებებს."
    },
    {
      "provision_ref": "art4",
      "section": "4",
      "title": "მუხლი 4. დეპარტამენტის სტრუქტურული ქვედანაყოფები",
      "content": "დეპარტამენტის სტრუქტურული ქვედანაყოფებია:\nა) სამართლებრივი უზრუნველყოფის სამმართველო;\nბ) სახელშეკრულებო ვალდებულებათა მონიტორინგის სამმართველო."
    },
    {
      "provision_ref": "art5",
      "section": "5",
      "title": "მუხლი 5. დეპარტამენტის სტრუქტურული ქვედანაყოფების კომპეტენციები",
      "content": "1. სამართლებრივი უზრუნველყოფის სამმართველო ახორციელებს:\nა) სასამართლო დავებზე სამინისტროს წარმომადგენლობის უზრუნველყოფას;\nბ) სამინისტროში შემოსული საჩივრებისა და სამინისტროს საქმიანობასთან დაკავშირებული სამართლებრივი დავების ანალიზის საფუძველზე წინადადებების მომზადებას და აღნიშნული დავების განხილვაში მონაწილეობის მიღებას;\nგ) ნორმატიული აქტების სისტემატიზაციისა და შესრულების მიზნით, ნორმატიული აქტების და მათში შეტანილი ცვლილებების შესწავლას და აღრიცხვას;\nდ) სამინისტროს საპარლამენტო მდივნის საქმიანობის უზრუნველყოფას;\nე) სხვა უწყებებიდან შემოსული, აგრეთვე სამინისტროს სტრუქტურული ქვედანაყოფებისა და სამინისტროს სისტემაში შემავალი დაწესებულებების მიერ შემუშავებული ნორმატიული აქტების პროექტებზე სამართლებრივი დასკვნების მომზადებას;\nვ) სამინისტროს სტრუქტურული ქვედანაყოფებისა და საჭიროების შემთხვევაში სამინისტროს სისტემაში შემავალი დაწესებულებების სამართლებრივ უზრუნველყოფას;\nზ) სამინისტროს სტრუქტურული ქვედანაყოფებისა და სამინისტროს სისტემაში შემავალი სახელმწიფო საქვეუწყებო დაწესებულების მიერ მომზადებული საკანონმდებლო აქტების პროექტების კანონმდებლობით დადგენილი წესით საქართველოს მთავრობაში წარდგენის პროცედურების ორგანიზებას;\nთ) სამინისტროს კანონშემოქმედებითი საქმიანობის გეგმით გათვალისწინებული საკითხების დადგენილ ვადებში გადაწყვეტის ორგანიზებას;\nი) თავის კომპენტეციის ფარგლებში წარადგინოს წინადადებები ნორმატიულ აქტების შემუშავებისა და მოქმედ ნორმატიულ აქტებში ცვლილებებისა და დამატებების შეტანის თაობაზე;\nკ) სამმართველოში შემოსულ ოფიციალურ კორესპონდენციებზე, მოქალაქეთა წერილებსა და განცხადებებზე სათანადო რეაგირებას;\nლ) მოქმედი კანონმდებლობით გათვალისწინებულ სხვა უფლებამოსილებებს.\n2. სახელშეკრულებო ვალდებულებათა მონიტორინგის სამმართველო ახორციელებს:\nა) სამინისტროს მიერ დადებული ხელშეკრულებებისა და ნაკისრი სახელშეკრულებო ვალდებულებების შესახებ მონაცემთა ერთიანი ბაზის შექმნისა და მისი პერიოდულად განახლების ორგანიზებას;\nბ) სამინისტროს მიერ დასადები ხელშეკრულების სამართლებრივ ექსპერტიზას (გარდა შრომითი და სახელმწიფო შესყიდვის შესახებ ხელშეკრულებებისა);\nგ) საკუთარი კომპეტენციის ფარგლებში, სამინისტროს მიერ ნაკისრ სახელშეკრულებო ვალდებულებათა (გარდა შრომითი და სახელმწიფო შესყიდვის შესახებ ხელშეკრულებებისა) მონიტორინგის განხორციელება\\ორგანიზებას, ასევე, ინსპექტირების ჯგუფის ან კოორდინატორის მიერ დაფიქსირებულ სახელმწიფო შესყიდვის ხელშეკრულებით გათვალისწინებული ვალდებულებების დარღვევებზე შესაბამის რეაგირებას, მოქმედი კანონმდებლობით დადგენილი წესით;\nდ) ხელშეკრულებების ანალიზის საფუძველზე დასკვნების შემუშავებას და წინადადებების მომზადებას განსახორციელებელი ღონისძიებების შესახებ;\nე) სამინისტროს სტრუქტურული ქვედანაყოფებისა და სამინისტროს სისტემაში შემავალი დაწესებულებებისგან, სხვა ფიზიკური და იურიდიული პირებისგან შესაბამისი ინფორმაციის გამოთხოვას;\nვ) შემოსული კორესპონდეციის განხილვას და შესაბამის რეაგირებას."
    },
    {
      "provision_ref": "art6",
      "section": "6",
      "title": "მუხლი 6. დეპარტამენტის სტრუქტურული ქვედანაყოფების ხელმძღვანელობა",
      "content": "1. დეპარტამენტში შემავალ სამმართველოებს ხელმძღვანელობს სამმართველოს უფროსი, რომელსაც კანონმდებლობით დადგენილი წესით თანამდებობაზე ნიშნავს და თანამდებობიდან ათავისუფლებს მინისტრი.\n2. სამმართველოს უფროსი:\nა) სამმართველოს უფლებამოსილების ფარგლებში წარმართავს სამმართველოს საქმიანობას;\nბ) ანაწილებს სამმართველოში შემოსულ მასალებს;\nგ) ახორციელებს ზედამხედველობას სამმართველოს მოსამსახურეთა მიერ სამსახურებრვი მოვალეობების შესრულებაზე;\nდ) მოთხოვნის შემთხვევაში ანგარიშს წარუდგენს დეპარტამენტის ხელმძღვანელობას სამმართველოს მიერ გაწეული მუშაობის თაობაზე;\nე) ახორციელებს მინისტრის, მინისტრის მოადგილის, დეპარტამენტის უფროსისა და დეპარტამენტის უფროსის მოადგილის ცალკეულ დავალებებს.\n3. სამმართველოს უფროსს ჰყავს მოადგილე, რომელსაც დადგენილი წესით თანამდებობაზე ნიშნავს და თანამდებობიდან ათავისუფლებს მინისტრი.\n4. სამმართველოს უფროსის მოადგილე:\nა) ანგარიშვალდებულია სამმართველოს უფროსის წინაშე, ათანხმებს მასთან საკუთარ გადაწყვეტილებებს სამმართველოს მუშაობის წარმართვის თაობაზე;\nბ) ასრულებს სამმართველოს უფროსის უშუალო დავალებებს, რომელიც გამომდინარეობს სამინისტროს საქმიანობის მიზნებიდან;\nგ) ასრულებს სამმართველოს უფროსის მოვალეობებს მის მიერ უფლებამოსილებათა განხორციელების შეუძლებლობის ან მისი არყოფნის შემთხვევაში.\n5. დეპარტამენტში შემავალი სამმართველოს უფროსები ანგარიშვალდებულნი არიან დეპარტამენტის ხელმძღვანელობის წინაშე."
    }
  ],
  "definitions": []
}
